odoo9_addon_account_invoice_supplier_ref_unique-9.0.1.0.0-py2.7-nspkg.pth
odoo_addons/account_invoice_supplier_ref_unique/__openerp__.py
odoo_addons/account_invoice_supplier_ref_unique/__init__.py
odoo_addons/account_invoice_supplier_ref_unique/README.rst
odoo_addons/account_invoice_supplier_ref_unique/models/account_invoice.py
odoo_addons/account_invoice_supplier_ref_unique/models/__init__.py
odoo_addons/account_invoice_supplier_ref_unique/i18n/sl.po
odoo_addons/account_invoice_supplier_ref_unique/i18n/fr.po
odoo_addons/account_invoice_supplier_ref_unique/i18n/account_invoice_supplier_ref_unique.pot
odoo_addons/account_invoice_supplier_ref_unique/views/account_invoice.xml
odoo_addons/account_invoice_supplier_ref_unique/tests/__init__.py
odoo_addons/account_invoice_supplier_ref_unique/tests/test_account_invoice_supplier_ref_unique.py
odoo9_addon_account_invoice_supplier_ref_unique-9.0.1.0.0.dist-info/top_level.txt
odoo9_addon_account_invoice_supplier_ref_unique-9.0.1.0.0.dist-info/WHEEL
odoo9_addon_account_invoice_supplier_ref_unique-9.0.1.0.0.dist-info/RECORD
odoo9_addon_account_invoice_supplier_ref_unique-9.0.1.0.0.dist-info/metadata.json
odoo9_addon_account_invoice_supplier_ref_unique-9.0.1.0.0.dist-info/DESCRIPTION.rst
odoo9_addon_account_invoice_supplier_ref_unique-9.0.1.0.0.dist-info/METADATA
odoo9_addon_account_invoice_supplier_ref_unique-9.0.1.0.0.dist-info/namespace_packages.txt
